advanced_reports/__init__.py
advanced_reports/decorators.py
advanced_reports/defaults.py
advanced_reports/models.py
advanced_reports/urls.py
advanced_reports/utils.py
advanced_reports/views.py
advanced_reports/backoffice/__init__.py
advanced_reports/backoffice/admin.py
advanced_reports/backoffice/api_utils.py
advanced_reports/backoffice/base.py
advanced_reports/backoffice/conf.py
advanced_reports/backoffice/decorators.py
advanced_reports/backoffice/models.py
advanced_reports/backoffice/search.py
advanced_reports/backoffice/shortcuts.py
advanced_reports/backoffice/contrib/__init__.py
advanced_reports/backoffice/contrib/mixins.py
advanced_reports/backoffice/contrib/views.py
advanced_reports/backoffice/examples/__init__.py
advanced_reports/backoffice/examples/backoffice.py
advanced_reports/backoffice/examples/reports.py
advanced_reports/backoffice/examples/views.py
advanced_reports/backoffice/management/__init__.py
advanced_reports/backoffice/management/commands/__init__.py
advanced_reports/backoffice/management/commands/backoffice_clean_searchindex.py
advanced_reports/backoffice/migrations/0001_initial.py
advanced_reports/backoffice/migrations/__init__.py
advanced_reports/backoffice/templatetags/__init__.py
advanced_reports/backoffice/templatetags/backoffice_filters.py
advanced_reports/static/advanced_reports/css/advreport.css
advanced_reports/static/advanced_reports/css/core.css
advanced_reports/static/advanced_reports/css/jquery.mbox.css
advanced_reports/static/advanced_reports/css/show-notice.css
advanced_reports/static/advanced_reports/css/ui.datepicker.css
advanced_reports/static/advanced_reports/fonts/glyphicons-halflings-regular.eot
advanced_reports/static/advanced_reports/fonts/glyphicons-halflings-regular.svg
advanced_reports/static/advanced_reports/fonts/glyphicons-halflings-regular.ttf
advanced_reports/static/advanced_reports/fonts/glyphicons-halflings-regular.woff
django_advanced_reports-0.9.24.dist-info/DESCRIPTION.rst
django_advanced_reports-0.9.24.dist-info/METADATA
django_advanced_reports-0.9.24.dist-info/RECORD
django_advanced_reports-0.9.24.dist-info/WHEEL
django_advanced_reports-0.9.24.dist-info/metadata.json
django_advanced_reports-0.9.24.dist-info/top_level.txt
