Metadata-Version: 2.0
Name: django-advanced-reports
Version: 0.9.24
Summary: Advanced reports for Django
Home-page: https://github.com/vikingco/django-advanced-reports
Author: Jef Geskens, Unleashed NV
Author-email: operations@unleashed.be
License: BSD
Platform: UNKNOWN
Classifier: Intended Audience :: Developers
Classifier: Programming Language :: Python
Classifier: Operating System :: OS Independent
Classifier: Environment :: Web Environment
Classifier: Framework :: Django
Requires-Dist: Django
Requires-Dist: django-widget-tweaks
Requires-Dist: pygments
Requires-Dist: six
